cfm/__init__.py
cfm/cli.py
cfm/engine/__init__.py
cfm/engine/filewalker.py
cfm/engine/transformer.py
cfm/utils/__init__.py
cfm/utils/config.py
cfm/utils/generator.py
cfm/utils/htmlreport.py
cfm/utils/installer.py
cfm/utils/publish.py
cfm/utils/registry.py
cfm/utils/ruleloader.py
cfm/utils/scaffold.py
cfm/utils/testrunner.py
cfm/utils/validator.py
cfm/utils/vscode.py
cfm/utils/watcher.py
codefixit_manager-1.11.0.dist-info/licenses/LICENSE
codefixit_manager-1.11.0.dist-info/METADATA
codefixit_manager-1.11.0.dist-info/WHEEL
codefixit_manager-1.11.0.dist-info/entry_points.txt
codefixit_manager-1.11.0.dist-info/top_level.txt
codefixit_manager-1.11.0.dist-info/RECORD
