Metadata-Version: 2.4
Name: codefixit-manager
Version: 1.11.0
Summary: 🛠️ A powerful CLI to modernize and refactor codebases using customizable rule packs.
Home-page: https://github.com/nyigoro/codefixit-manager
Author: Nyigoro
Author-email: nyigoro <nyigoro@gmail.com>
License: MIT
Keywords: refactor,cli,modernizer,codefix,qt5to6,cfm
Requires-Python: >=3.7
License-File: LICENSE
Requires-Dist: colorama
Requires-Dist: rich
Requires-Dist: requests
Requires-Dist: openai
Requires-Dist: watchdog
Dynamic: author
Dynamic: home-page
Dynamic: license-file
Dynamic: requires-python
